phy_poetry/__init__.py
phy_poetry-0.1.4.dist-info/LICENSE.md
phy_poetry-0.1.4.dist-info/METADATA
phy_poetry-0.1.4.dist-info/WHEEL
phy_poetry-0.1.4.dist-info/RECORD
